juliet/KeplerOrbit.py
juliet/__init__.py
juliet/__main__.py
juliet/_version.py
juliet/fit.py
juliet/plots.py
juliet/test_utils.py
juliet/utils.py
juliet-2.2.8.dist-info/AUTHORS.rst
juliet-2.2.8.dist-info/LICENSE
juliet-2.2.8.dist-info/METADATA
juliet-2.2.8.dist-info/WHEEL
juliet-2.2.8.dist-info/entry_points.txt
juliet-2.2.8.dist-info/top_level.txt
juliet-2.2.8.dist-info/RECORD
