Metadata-Version: 2.1
Name: juliet
Version: 2.2.8
Summary: juliet: a versatile modelling tool for transiting exoplanets, radial-velocity systems or both
Home-page: http://github.com/nespinoza/juliet
Author: Nestor Espinoza
Author-email: nespinoza@stsci.edu
License: MIT
Requires-Python: >=2.7
License-File: LICENSE
License-File: AUTHORS.rst
Requires-Dist: batman-package
Requires-Dist: radvel
Requires-Dist: dynesty (>=1.2.2)
Requires-Dist: george
Requires-Dist: celerite
Requires-Dist: astropy
Requires-Dist: numpy
Requires-Dist: scipy
Requires-Dist: emcee
Requires-Dist: ultranest
Requires-Dist: h5py
